fixedint/__init__.py
fixedint/__init__.pyi
fixedint/aliases.py
fixedint/aliases.pyi
fixedint/base.py
fixedint/base.pyi
fixedint/compat.py
fixedint/py.typed
fixedint/test_fixedint.py
fixedint/util.py
fixedint-0.2.0.dist-info/AUTHORS
fixedint-0.2.0.dist-info/LICENSE
fixedint-0.2.0.dist-info/METADATA
fixedint-0.2.0.dist-info/WHEEL
fixedint-0.2.0.dist-info/top_level.txt
fixedint-0.2.0.dist-info/RECORD
