Metadata-Version: 2.1
Name: fixedint
Version: 0.2.0
Summary: simple fixed-width integers
Home-page: https://github.com/nneonneo/fixedint
Author: Robert Xiao
Author-email: robert.bo.xiao@gmail.com
License: PSF
Platform: UNKNOWN
Classifier: License :: OSI Approved :: Python Software Foundation License
Classifier: Development Status :: 4 - Beta
Classifier: Intended Audience :: Developers
Classifier: Operating System :: OS Independent
Classifier: Programming Language :: Python :: 2
Classifier: Programming Language :: Python :: 2.7
Classifier: Programming Language :: Python :: 3
Classifier: Programming Language :: Python :: 3.5
Classifier: Programming Language :: Python :: 3.6
Classifier: Programming Language :: Python :: 3.7
Classifier: Programming Language :: Python :: 3.8
Classifier: Programming Language :: Python :: 3.9
Classifier: Programming Language :: Python :: 3.10
Classifier: Programming Language :: Python :: 3.11
Classifier: Topic :: Utilities
